rrxr/__init__.py
rrxr/rrxy.py
rrxr-1.0.dist-info/LICENSE
rrxr-1.0.dist-info/METADATA
rrxr-1.0.dist-info/WHEEL
rrxr-1.0.dist-info/top_level.txt
rrxr-1.0.dist-info/RECORD
