Metadata-Version: 2.1
Name: rrxr
Version: 1.0
Summary: - simple library with python
Home-page: https://github.com/A-X-1/test-lib
Author-email: alexcrow221@gmail.com
Classifier: Programming Language :: Python :: 3
Classifier: License :: OSI Approved :: MIT License
Classifier: Operating System :: OS Independent
Requires-Python: >=3.6
License-File: LICENSE
